duplicate/__init__.py
duplicate/apps.py
duplicate/checks.py
duplicate/duplicates.py
duplicate/exceptions.py
duplicate/models.py
duplicate/utils.py
django_duplicate-1.0.0.dist-info/METADATA
django_duplicate-1.0.0.dist-info/WHEEL
django_duplicate-1.0.0.dist-info/top_level.txt
django_duplicate-1.0.0.dist-info/RECORD
